pydantic_ai_helpers/__init__.py
pydantic_ai_helpers/evals/__init__.py
pydantic_ai_helpers/evals/accessors.py
pydantic_ai_helpers/evals/compare.py
pydantic_ai_helpers/evals/evaluators.py
pydantic_ai_helpers/evals/normalize.py
pydantic_ai_helpers/evals/registry.py
pydantic_ai_helpers/history.py
pydantic_ai_helpers/py.typed
pydantic_ai_helpers-0.0.2.dist-info/WHEEL
pydantic_ai_helpers-0.0.2.dist-info/METADATA
pydantic_ai_helpers-0.0.2.dist-info/RECORD
