Metadata-Version: 2.4
Name: pydantic-ai-helpers
Version: 0.0.2
Summary: Boring, opinionated helpers for PydanticAI that are so simple you didn't want to even vibe code them. (Unofficial)
Keywords: pydantic,ai,utilities,history,llm
Author: Jan Siml
Author-email: Jan Siml <49557684+svilupp@users.noreply.github.com>
License-Expression: MIT
Classifier: Development Status :: 4 - Beta
Classifier: Intended Audience :: Developers
Classifier: License :: OSI Approved :: MIT License
Classifier: Programming Language :: Python :: 3
Classifier: Programming Language :: Python :: 3.10
Classifier: Programming Language :: Python :: 3.11
Classifier: Programming Language :: Python :: 3.12
Classifier: Programming Language :: Python :: 3.13
Classifier: Topic :: Software Development :: Libraries :: Python Modules
Classifier: Typing :: Typed
Requires-Dist: pydantic-ai>=0.0.20
Requires-Dist: rapidfuzz>=3.13.0
Requires-Dist: pydantic-evals>=0.7.2
Requires-Dist: pytest>=8.0.0 ; extra == 'dev'
Requires-Dist: pytest-cov>=4.1.0 ; extra == 'dev'
Requires-Dist: pytest-asyncio>=0.21.0 ; extra == 'dev'
Requires-Dist: ruff>=0.5.0 ; extra == 'dev'
Requires-Dist: mypy>=1.8.0 ; extra == 'dev'
Requires-Dist: pre-commit>=3.5.0 ; extra == 'dev'
Requires-Dist: pydantic-core>=2.0.0 ; extra == 'dev'
Requires-Python: >=3.10
Project-URL: Changelog, https://github.com/yourusername/pydantic-ai-helpers/blob/main/CHANGELOG.md
Project-URL: Documentation, https://github.com/yourusername/pydantic-ai-helpers#readme
Project-URL: Homepage, https://github.com/yourusername/pydantic-ai-helpers
Project-URL: Issues, https://github.com/yourusername/pydantic-ai-helpers/issues
Project-URL: Repository, https://github.com/yourusername/pydantic-ai-helpers
Provides-Extra: dev
